llama_index/readers/docstring_walker/__init__.py
llama_index/readers/docstring_walker/base.py
llama_index_readers_docstring_walker-0.4.1.dist-info/METADATA
llama_index_readers_docstring_walker-0.4.1.dist-info/WHEEL
llama_index_readers_docstring_walker-0.4.1.dist-info/licenses/LICENSE
llama_index_readers_docstring_walker-0.4.1.dist-info/RECORD
