Metadata-Version: 2.4
Name: llama-index-readers-docstring-walker
Version: 0.4.1
Summary: llama-index readers docstring_walker integration
Author-email: Your Name <you@example.com>
Maintainer: Filip Wojcik
License-Expression: MIT
License-File: LICENSE
Keywords: code,docstring,python,source code
Requires-Python: <4.0,>=3.9
Requires-Dist: llama-index-core<0.15,>=0.13.0
